GOP/__init__.py
GOP/version.py
GOP/layers/__init__.py
GOP/layers/gop.py
GOP/models/__init__.py
GOP/models/_model.py
GOP/models/hemlgop.py
GOP/models/hemlrn.py
GOP/models/homlgop.py
GOP/models/homlrn.py
GOP/models/pop.py
GOP/models/popfast.py
GOP/models/popmemh.py
GOP/models/popmemo.py
GOP/utility/__init__.py
GOP/utility/block_update.py
GOP/utility/calculate_memory.py
GOP/utility/gop_operators.py
GOP/utility/gop_search.py
GOP/utility/gop_search_gpu.py
GOP/utility/gop_utils.py
GOP/utility/misc.py
pygop-0.2.3.dist-info/LICENSE.txt
pygop-0.2.3.dist-info/METADATA
pygop-0.2.3.dist-info/WHEEL
pygop-0.2.3.dist-info/top_level.txt
pygop-0.2.3.dist-info/RECORD
