Metadata-Version: 2.1
Name: pygop
Version: 0.2.3
Summary: Python package that implements various algorithms using Generalized Operational Perceptron
Home-page: https://github.com/viebboy/PyGOP
Author: Dat Tran, Alexandros Iosifidis
Author-email: viebboy@gmail.com, iosifidis.alekos@gmail.com
License: LICENSE.txt
Platform: UNKNOWN
Classifier: Operating System :: POSIX
Requires-Dist: python-version (>="2.7")
Requires-Dist: numpy (>=1.13)
Requires-Dist: dill (>=0.2.6)
Requires-Dist: joblib (>=0.11)
Requires-Dist: keras (==2.2.4)
